django_journal/__init__.py
django_journal/actions.py
django_journal/admin.py
django_journal/decorator.py
django_journal/exceptions.py
django_journal/journal.py
django_journal/managers.py
django_journal/middleware.py
django_journal/models.py
django_journal/locale/fr/LC_MESSAGES/django.po
django_journal/migrations/0001_initial.py
django_journal/migrations/__init__.py
django_journal/static/journal/css/journal.css
django_journal/static/journal/images/external-link-ltr-icon.png
django_journal-3.dist-info/METADATA
django_journal-3.dist-info/WHEEL
django_journal-3.dist-info/top_level.txt
django_journal-3.dist-info/RECORD
